{"12": {"tablero": [[1, 3, 4, 0], [4, 2, 0, 0], [0, 4, 1, 0], [0, 1, 0, 4]], "puntaje": 30, "nivel": 2, "dificultad": 1, "terminada": false}, "33": {"tablero": [[2, 0, 7, 0, 0, 0, 0, 0, 0], [8, 0, 0, 0, 0, 3, 0, 4, 0], [0, 0, 0, 0, 2, 0, 5, 0, 0], [6, 0, 0, 9, 3, 5, 0, 0, 0], [0, 0, 0, 0, 4, 0, 8, 0, 6], [0, 0, 0, 0, 0, 0, 0, 0, 5], [0, 0, 0, 0, 0, 0, 9, 0, 0], [0, 0, 0, 0, 0, 0, 0, 0, 0], [4, 8, 0, 0, 0, 0, 0, 0, 0]], "puntaje": 150, "nivel": 3, "dificultad": 3, "terminada": false}, "23": {"tablero": [[0, 3, 4, 0], [0, 0, 0, 0], [0, 0, 0, 0], [1, 0, 0, 2]], "puntaje": -270, "nivel": 2, "dificultad": 3, "terminada": false}, "leonardo-montoya - 23": {"name": "leonardo-montoya", "tablero": [[3, 2, 4, 0], [1, 4, 0, 0], [2, 0, 0, 0], [0, 3, 0, 0]], "puntaje": 350, "nivel": 2, "dificultad": 3, "terminada": false}}